odoo/addons/crm_partner_required/README.rst
odoo/addons/crm_partner_required/__init__.py
odoo/addons/crm_partner_required/__manifest__.py
odoo/addons/crm_partner_required/i18n/crm_partner_required.pot
odoo/addons/crm_partner_required/i18n/it.po
odoo/addons/crm_partner_required/readme/CONTEXT.md
odoo/addons/crm_partner_required/readme/CONTRIBUTORS.md
odoo/addons/crm_partner_required/readme/DESCRIPTION.md
odoo/addons/crm_partner_required/readme/USAGE.md
odoo/addons/crm_partner_required/static/description/icon.png
odoo/addons/crm_partner_required/static/description/index.html
odoo/addons/crm_partner_required/tests/__init__.py
odoo/addons/crm_partner_required/tests/test_crm_partner_required.py
odoo/addons/crm_partner_required/views/crm_lead_view.xml
odoo_addon_crm_partner_required-18.0.1.0.2.dist-info/METADATA
odoo_addon_crm_partner_required-18.0.1.0.2.dist-info/WHEEL
odoo_addon_crm_partner_required-18.0.1.0.2.dist-info/top_level.txt
odoo_addon_crm_partner_required-18.0.1.0.2.dist-info/RECORD
